README.md
setup.py
mathproblem/__init__.py
mathproblem/algebra.py
mathproblem/graph_transforms.py
mathproblem/point2.py
mathproblem/problem.py
mathproblem/right_angle.py
mathproblem/right_triangle_diagram.py
mathproblem/simple_svg.py
mathproblem/trig.py
mathproblem/trig_defs.py
mathproblem/unit_circle_eval.py
mathproblem/unit_circle_graph.py
mathproblem.egg-info/PKG-INFO
mathproblem.egg-info/SOURCES.txt
mathproblem.egg-info/dependency_links.txt
mathproblem.egg-info/not-zip-safe
mathproblem.egg-info/top_level.txt