Metadata-Version: 1.1
Name: mathproblem
Version: 0.1.3
Summary: Easily generate math problems
Home-page: https://github.com/matthewcpp/mathproblem
Author: Matthew LaRocca
Author-email: mlarocca.cpp@gmail.com
License: MIT
Platform: UNKNOWN
Classifier: Development Status :: 3 - Alpha
